{
  "date": "2026-04-22",
  "signals": [
    {
      "ticker": "007660",
      "name": "이수페타시스",
      "market": "KOSPI",
      "score": 10,
      "flow_score": 5,
      "trend_score": 3,
      "vol_score": 2,
      "foreign_flow": 723.8,
      "institution_flow": 217.1,
      "volume_ratio": 6.27,
      "signal_strength": "strong",
      "signal_date": "2026-04-22",
      "price": 161400.0,
      "change_pct": 21.17,
      "ma20": 117155,
      "ma60": 115357.0,
      "trend": "above_both"
    },
    {
      "ticker": "000500",
      "name": "가온전선",
      "market": "KOSPI",
      "score": 10,
      "flow_score": 5,
      "trend_score": 3,
      "vol_score": 2,
      "foreign_flow": 142.5,
      "institution_flow": 186.2,
      "volume_ratio": 3.49,
      "signal_strength": "strong",
      "signal_date": "2026-04-22",
      "price": 180000.0,
      "change_pct": 15.83,
      "ma20": 117770,
      "ma60": 103845.0,
      "trend": "above_both"
    },
    {
      "ticker": "336260",
      "name": "두산퓨얼셀",
      "market": "KOSPI",
      "score": 9,
      "flow_score": 5,
      "trend_score": 3,
      "vol_score": 1,
      "foreign_flow": 216.2,
      "institution_flow": 42.2,
      "volume_ratio": 2.88,
      "signal_strength": "strong",
      "signal_date": "2026-04-22",
      "price": 48250.0,
      "change_pct": 11.3,
      "ma20": 39342,
      "ma60": 38588.0,
      "trend": "above_both"
    },
    {
      "ticker": "020150",
      "name": "롯데에너지머티리얼즈",
      "market": "KOSPI",
      "score": 9,
      "flow_score": 5,
      "trend_score": 3,
      "vol_score": 1,
      "foreign_flow": 181.8,
      "institution_flow": 163.6,
      "volume_ratio": 2.97,
      "signal_strength": "strong",
      "signal_date": "2026-04-22",
      "price": 62100.0,
      "change_pct": 9.52,
      "ma20": 46530,
      "ma60": 42952.0,
      "trend": "above_both"
    },
    {
      "ticker": "006110",
      "name": "삼아알미늄",
      "market": "KOSPI",
      "score": 8,
      "flow_score": 4,
      "trend_score": 3,
      "vol_score": 1,
      "foreign_flow": 119.6,
      "institution_flow": 63.8,
      "volume_ratio": 2.88,
      "signal_strength": "strong",
      "signal_date": "2026-04-22",
      "price": 71300.0,
      "change_pct": 21.88,
      "ma20": 45690,
      "ma60": 35685.0,
      "trend": "above_both"
    },
    {
      "ticker": "322000",
      "name": "HD현대에너지솔루션",
      "market": "KOSPI",
      "score": 8,
      "flow_score": 4,
      "trend_score": 3,
      "vol_score": 1,
      "foreign_flow": 60.8,
      "institution_flow": 53.7,
      "volume_ratio": 2.16,
      "signal_strength": "strong",
      "signal_date": "2026-04-22",
      "price": 182400.0,
      "change_pct": 7.29,
      "ma20": 158570,
      "ma60": 114070.0,
      "trend": "above_both"
    },
    {
      "ticker": "417840",
      "name": "저스템",
      "market": "KOSDAQ",
      "score": 8,
      "flow_score": 4,
      "trend_score": 3,
      "vol_score": 1,
      "foreign_flow": 31.4,
      "institution_flow": 129.7,
      "volume_ratio": 2.79,
      "signal_strength": "strong",
      "signal_date": "2026-04-22",
      "price": 12260.0,
      "change_pct": 11.25,
      "ma20": 7894,
      "ma60": 7095.0,
      "trend": "above_both"
    },
    {
      "ticker": "112610",
      "name": "씨에스윈드",
      "market": "KOSPI",
      "score": 7,
      "flow_score": 4,
      "trend_score": 3,
      "vol_score": 0,
      "foreign_flow": 116.4,
      "institution_flow": 53.4,
      "volume_ratio": 1.47,
      "signal_strength": "strong",
      "signal_date": "2026-04-22",
      "price": 69400.0,
      "change_pct": 8.78,
      "ma20": 65485,
      "ma60": 54704.0,
      "trend": "above_both"
    },
    {
      "ticker": "017860",
      "name": "DS단석",
      "market": "KOSPI",
      "score": 7,
      "flow_score": 2,
      "trend_score": 3,
      "vol_score": 2,
      "foreign_flow": 0.2,
      "institution_flow": 0.2,
      "volume_ratio": 11.13,
      "signal_strength": "moderate",
      "signal_date": "2026-04-22",
      "price": 26250.0,
      "change_pct": 29.95,
      "ma20": 19856,
      "ma60": 19424.0,
      "trend": "above_both"
    },
    {
      "ticker": "161000",
      "name": "애경케미칼",
      "market": "KOSPI",
      "score": 7,
      "flow_score": 2,
      "trend_score": 3,
      "vol_score": 2,
      "foreign_flow": 5.9,
      "institution_flow": 8.9,
      "volume_ratio": 4.66,
      "signal_strength": "moderate",
      "signal_date": "2026-04-22",
      "price": 19100.0,
      "change_pct": 24.35,
      "ma20": 13682,
      "ma60": 11221.0,
      "trend": "above_both"
    },
    {
      "ticker": "005090",
      "name": "SGC에너지",
      "market": "KOSPI",
      "score": 7,
      "flow_score": 2,
      "trend_score": 3,
      "vol_score": 2,
      "foreign_flow": 76.7,
      "institution_flow": -67.4,
      "volume_ratio": 3.8,
      "signal_strength": "moderate",
      "signal_date": "2026-04-22",
      "price": 63500.0,
      "change_pct": 20.27,
      "ma20": 55880,
      "ma60": 46653.0,
      "trend": "above_both"
    },
    {
      "ticker": "010820",
      "name": "퍼스텍",
      "market": "KOSPI",
      "score": 7,
      "flow_score": 2,
      "trend_score": 3,
      "vol_score": 2,
      "foreign_flow": -115.2,
      "institution_flow": 175.7,
      "volume_ratio": 3.38,
      "signal_strength": "moderate",
      "signal_date": "2026-04-22",
      "price": 16360.0,
      "change_pct": 13.53,
      "ma20": 10176,
      "ma60": 7580.0,
      "trend": "above_both"
    },
    {
      "ticker": "097230",
      "name": "HJ중공업",
      "market": "KOSPI",
      "score": 7,
      "flow_score": 2,
      "trend_score": 3,
      "vol_score": 2,
      "foreign_flow": -127.1,
      "institution_flow": 7.1,
      "volume_ratio": 5.93,
      "signal_strength": "moderate",
      "signal_date": "2026-04-22",
      "price": 31000.0,
      "change_pct": 10.71,
      "ma20": 25625,
      "ma60": 25252.0,
      "trend": "above_both"
    },
    {
      "ticker": "171120",
      "name": "라이온켐텍",
      "market": "KOSDAQ",
      "score": 7,
      "flow_score": 2,
      "trend_score": 3,
      "vol_score": 2,
      "foreign_flow": 2.9,
      "institution_flow": 0.6,
      "volume_ratio": 16.42,
      "signal_strength": "moderate",
      "signal_date": "2026-04-22",
      "price": 2925.0,
      "change_pct": 30.0,
      "ma20": 2144,
      "ma60": 2116.0,
      "trend": "above_both"
    },
    {
      "ticker": "163730",
      "name": "핑거",
      "market": "KOSDAQ",
      "score": 7,
      "flow_score": 2,
      "trend_score": 3,
      "vol_score": 2,
      "foreign_flow": 14.8,
      "institution_flow": 0.5,
      "volume_ratio": 10.9,
      "signal_strength": "moderate",
      "signal_date": "2026-04-22",
      "price": 18070.0,
      "change_pct": 30.0,
      "ma20": 11104,
      "ma60": 11069.0,
      "trend": "above_both"
    },
    {
      "ticker": "125210",
      "name": "아모그린텍",
      "market": "KOSDAQ",
      "score": 7,
      "flow_score": 2,
      "trend_score": 3,
      "vol_score": 2,
      "foreign_flow": 2.2,
      "institution_flow": 15.7,
      "volume_ratio": 4.6,
      "signal_strength": "moderate",
      "signal_date": "2026-04-22",
      "price": 12720.0,
      "change_pct": 18.11,
      "ma20": 9008,
      "ma60": 7848.0,
      "trend": "above_both"
    },
    {
      "ticker": "417200",
      "name": "LS머트리얼즈",
      "market": "KOSDAQ",
      "score": 7,
      "flow_score": 2,
      "trend_score": 3,
      "vol_score": 2,
      "foreign_flow": -42.8,
      "institution_flow": 61.2,
      "volume_ratio": 3.51,
      "signal_strength": "moderate",
      "signal_date": "2026-04-22",
      "price": 25150.0,
      "change_pct": 10.55,
      "ma20": 20711,
      "ma60": 18662.0,
      "trend": "above_both"
    },
    {
      "ticker": "011070",
      "name": "LG이노텍",
      "market": "KOSPI",
      "score": 6,
      "flow_score": 2,
      "trend_score": 3,
      "vol_score": 1,
      "foreign_flow": -811.4,
      "institution_flow": 1316.1,
      "volume_ratio": 2.81,
      "signal_strength": "moderate",
      "signal_date": "2026-04-22",
      "price": 500000.0,
      "change_pct": 17.65,
      "ma20": 358675,
      "ma60": 295992.0,
      "trend": "above_both"
    },
    {
      "ticker": "082740",
      "name": "한화엔진",
      "market": "KOSPI",
      "score": 6,
      "flow_score": 2,
      "trend_score": 2,
      "vol_score": 2,
      "foreign_flow": -761.7,
      "institution_flow": 894.4,
      "volume_ratio": 4.19,
      "signal_strength": "moderate",
      "signal_date": "2026-04-22",
      "price": 67500.0,
      "change_pct": 11.39,
      "ma20": 48688,
      "ma60": 51088.0,
      "trend": "above_both"
    },
    {
      "ticker": "033240",
      "name": "자화전자",
      "market": "KOSPI",
      "score": 6,
      "flow_score": 2,
      "trend_score": 2,
      "vol_score": 2,
      "foreign_flow": -100.4,
      "institution_flow": 154.7,
      "volume_ratio": 3.02,
      "signal_strength": "moderate",
      "signal_date": "2026-04-22",
      "price": 46250.0,
      "change_pct": 7.56,
      "ma20": 36550,
      "ma60": 37192.0,
      "trend": "above_both"
    },
    {
      "ticker": "100790",
      "name": "미래에셋벤처투자",
      "market": "KOSDAQ",
      "score": 6,
      "flow_score": 2,
      "trend_score": 3,
      "vol_score": 1,
      "foreign_flow": -76.4,
      "institution_flow": 69.7,
      "volume_ratio": 2.53,
      "signal_strength": "moderate",
      "signal_date": "2026-04-22",
      "price": 57700.0,
      "change_pct": 21.86,
      "ma20": 34170,
      "ma60": 25704.0,
      "trend": "above_both"
    },
    {
      "ticker": "307180",
      "name": "아이엘",
      "market": "KOSDAQ",
      "score": 6,
      "flow_score": 2,
      "trend_score": 2,
      "vol_score": 2,
      "foreign_flow": 9.4,
      "institution_flow": 0.9,
      "volume_ratio": 3.61,
      "signal_strength": "moderate",
      "signal_date": "2026-04-22",
      "price": 6360.0,
      "change_pct": 17.78,
      "ma20": 5110,
      "ma60": 5221.0,
      "trend": "above_both"
    },
    {
      "ticker": "469610",
      "name": "이노테크",
      "market": "KOSDAQ",
      "score": 6,
      "flow_score": 2,
      "trend_score": 2,
      "vol_score": 2,
      "foreign_flow": -51.7,
      "institution_flow": 53.4,
      "volume_ratio": 9.65,
      "signal_strength": "moderate",
      "signal_date": "2026-04-22",
      "price": 30650.0,
      "change_pct": 16.98,
      "ma20": 20224,
      "ma60": 21770.0,
      "trend": "above_both"
    },
    {
      "ticker": "027360",
      "name": "아주IB투자",
      "market": "KOSDAQ",
      "score": 6,
      "flow_score": 2,
      "trend_score": 3,
      "vol_score": 1,
      "foreign_flow": -311.3,
      "institution_flow": 1.0,
      "volume_ratio": 2.86,
      "signal_strength": "moderate",
      "signal_date": "2026-04-22",
      "price": 14150.0,
      "change_pct": 16.75,
      "ma20": 9978,
      "ma60": 6872.0,
      "trend": "above_both"
    },
    {
      "ticker": "131970",
      "name": "두산테스나",
      "market": "KOSDAQ",
      "score": 6,
      "flow_score": 2,
      "trend_score": 3,
      "vol_score": 1,
      "foreign_flow": -269.5,
      "institution_flow": 70.1,
      "volume_ratio": 2.18,
      "signal_strength": "moderate",
      "signal_date": "2026-04-22",
      "price": 124900.0,
      "change_pct": 15.65,
      "ma20": 99800,
      "ma60": 79910.0,
      "trend": "above_both"
    },
    {
      "ticker": "214430",
      "name": "아이쓰리시스템",
      "market": "KOSDAQ",
      "score": 6,
      "flow_score": 2,
      "trend_score": 2,
      "vol_score": 2,
      "foreign_flow": 1.3,
      "institution_flow": -148.7,
      "volume_ratio": 3.2,
      "signal_strength": "moderate",
      "signal_date": "2026-04-22",
      "price": 112400.0,
      "change_pct": 12.96,
      "ma20": 98035,
      "ma60": 104677.0,
      "trend": "above_both"
    },
    {
      "ticker": "484590",
      "name": "삼양컴텍",
      "market": "KOSDAQ",
      "score": 6,
      "flow_score": 2,
      "trend_score": 2,
      "vol_score": 2,
      "foreign_flow": 11.7,
      "institution_flow": 7.7,
      "volume_ratio": 8.33,
      "signal_strength": "moderate",
      "signal_date": "2026-04-22",
      "price": 14100.0,
      "change_pct": 12.44,
      "ma20": 12224,
      "ma60": 12597.0,
      "trend": "above_both"
    },
    {
      "ticker": "323280",
      "name": "태성",
      "market": "KOSDAQ",
      "score": 6,
      "flow_score": 2,
      "trend_score": 2,
      "vol_score": 2,
      "foreign_flow": -186.9,
      "institution_flow": 10.9,
      "volume_ratio": 3.49,
      "signal_strength": "moderate",
      "signal_date": "2026-04-22",
      "price": 74200.0,
      "change_pct": 12.08,
      "ma20": 56455,
      "ma60": 65679.0,
      "trend": "above_both"
    },
    {
      "ticker": "052710",
      "name": "아모텍",
      "market": "KOSDAQ",
      "score": 6,
      "flow_score": 2,
      "trend_score": 3,
      "vol_score": 1,
      "foreign_flow": -22.2,
      "institution_flow": 96.6,
      "volume_ratio": 2.08,
      "signal_strength": "moderate",
      "signal_date": "2026-04-22",
      "price": 27950.0,
      "change_pct": 10.91,
      "ma20": 18908,
      "ma60": 14106.0,
      "trend": "above_both"
    },
    {
      "ticker": "092220",
      "name": "KEC",
      "market": "KOSPI",
      "score": 6,
      "flow_score": 1,
      "trend_score": 3,
      "vol_score": 2,
      "foreign_flow": -43.3,
      "institution_flow": 1.8,
      "volume_ratio": 5.02,
      "signal_strength": "weak",
      "signal_date": "2026-04-22",
      "price": 1843.0,
      "change_pct": 29.97,
      "ma20": 1518,
      "ma60": 1240.0,
      "trend": "above_both"
    },
    {
      "ticker": "001250",
      "name": "GS글로벌",
      "market": "KOSPI",
      "score": 6,
      "flow_score": 1,
      "trend_score": 3,
      "vol_score": 2,
      "foreign_flow": -22.0,
      "institution_flow": 5.6,
      "volume_ratio": 3.66,
      "signal_strength": "weak",
      "signal_date": "2026-04-22",
      "price": 3950.0,
      "change_pct": 17.21,
      "ma20": 3204,
      "ma60": 2728.0,
      "trend": "above_both"
    },
    {
      "ticker": "093640",
      "name": "케이알엠",
      "market": "KOSDAQ",
      "score": 6,
      "flow_score": 1,
      "trend_score": 3,
      "vol_score": 2,
      "foreign_flow": 2.2,
      "institution_flow": 0.0,
      "volume_ratio": 8.93,
      "signal_strength": "weak",
      "signal_date": "2026-04-22",
      "price": 5190.0,
      "change_pct": 24.46,
      "ma20": 4412,
      "ma60": 4312.0,
      "trend": "above_both"
    },
    {
      "ticker": "170920",
      "name": "엘티씨",
      "market": "KOSDAQ",
      "score": 6,
      "flow_score": 1,
      "trend_score": 3,
      "vol_score": 2,
      "foreign_flow": -12.2,
      "institution_flow": 34.4,
      "volume_ratio": 3.6,
      "signal_strength": "weak",
      "signal_date": "2026-04-22",
      "price": 41500.0,
      "change_pct": 14.48,
      "ma20": 31648,
      "ma60": 28103.0,
      "trend": "above_both"
    },
    {
      "ticker": "094840",
      "name": "슈프리마에이치큐",
      "market": "KOSDAQ",
      "score": 6,
      "flow_score": 1,
      "trend_score": 3,
      "vol_score": 2,
      "foreign_flow": -3.4,
      "institution_flow": 0.1,
      "volume_ratio": 8.28,
      "signal_strength": "weak",
      "signal_date": "2026-04-22",
      "price": 10300.0,
      "change_pct": 14.44,
      "ma20": 8409,
      "ma60": 7546.0,
      "trend": "above_both"
    },
    {
      "ticker": "236200",
      "name": "슈프리마",
      "market": "KOSDAQ",
      "score": 6,
      "flow_score": 1,
      "trend_score": 3,
      "vol_score": 2,
      "foreign_flow": 2.1,
      "institution_flow": -5.1,
      "volume_ratio": 4.19,
      "signal_strength": "weak",
      "signal_date": "2026-04-22",
      "price": 54000.0,
      "change_pct": 11.11,
      "ma20": 47492,
      "ma60": 47282.0,
      "trend": "above_both"
    },
    {
      "ticker": "378340",
      "name": "필에너지",
      "market": "KOSDAQ",
      "score": 6,
      "flow_score": 1,
      "trend_score": 3,
      "vol_score": 2,
      "foreign_flow": -5.1,
      "institution_flow": 3.1,
      "volume_ratio": 5.8,
      "signal_strength": "weak",
      "signal_date": "2026-04-22",
      "price": 21850.0,
      "change_pct": 10.63,
      "ma20": 15738,
      "ma60": 15441.0,
      "trend": "above_both"
    },
    {
      "ticker": "009540",
      "name": "HD한국조선해양",
      "market": "KOSPI",
      "score": 5,
      "flow_score": 2,
      "trend_score": 2,
      "vol_score": 1,
      "foreign_flow": -479.7,
      "institution_flow": 528.9,
      "volume_ratio": 2.62,
      "signal_strength": "moderate",
      "signal_date": "2026-04-22",
      "price": 463000.0,
      "change_pct": 8.3,
      "ma20": 388525,
      "ma60": 406492.0,
      "trend": "above_both"
    },
    {
      "ticker": "012320",
      "name": "경동인베스트",
      "market": "KOSPI",
      "score": 5,
      "flow_score": 1,
      "trend_score": 2,
      "vol_score": 2,
      "foreign_flow": -4.1,
      "institution_flow": 0.7,
      "volume_ratio": 11.6,
      "signal_strength": "weak",
      "signal_date": "2026-04-22",
      "price": 70700.0,
      "change_pct": 12.76,
      "ma20": 58585,
      "ma60": 68798.0,
      "trend": "above_both"
    },
    {
      "ticker": "023790",
      "name": "동일스틸럭스",
      "market": "KOSDAQ",
      "score": 5,
      "flow_score": 1,
      "trend_score": 2,
      "vol_score": 2,
      "foreign_flow": 0.7,
      "institution_flow": 0.0,
      "volume_ratio": 6.29,
      "signal_strength": "weak",
      "signal_date": "2026-04-22",
      "price": 1305.0,
      "change_pct": 29.98,
      "ma20": 1014,
      "ma60": 1058.0,
      "trend": "above_both"
    },
    {
      "ticker": "187790",
      "name": "나노",
      "market": "KOSDAQ",
      "score": 5,
      "flow_score": 1,
      "trend_score": 2,
      "vol_score": 2,
      "foreign_flow": -6.0,
      "institution_flow": 44.0,
      "volume_ratio": 8.77,
      "signal_strength": "weak",
      "signal_date": "2026-04-22",
      "price": 5830.0,
      "change_pct": 24.44,
      "ma20": 3774,
      "ma60": 3966.0,
      "trend": "above_both"
    },
    {
      "ticker": "262260",
      "name": "에이프로",
      "market": "KOSDAQ",
      "score": 5,
      "flow_score": 1,
      "trend_score": 2,
      "vol_score": 2,
      "foreign_flow": 0.5,
      "institution_flow": -0.0,
      "volume_ratio": 13.0,
      "signal_strength": "weak",
      "signal_date": "2026-04-22",
      "price": 7050.0,
      "change_pct": 19.49,
      "ma20": 5280,
      "ma60": 5338.0,
      "trend": "above_both"
    },
    {
      "ticker": "273640",
      "name": "와이엠텍",
      "market": "KOSDAQ",
      "score": 5,
      "flow_score": 1,
      "trend_score": 2,
      "vol_score": 2,
      "foreign_flow": 1.3,
      "institution_flow": 0.0,
      "volume_ratio": 17.72,
      "signal_strength": "weak",
      "signal_date": "2026-04-22",
      "price": 10150.0,
      "change_pct": 18.85,
      "ma20": 7691,
      "ma60": 7710.0,
      "trend": "above_both"
    },
    {
      "ticker": "137950",
      "name": "제이씨케미칼",
      "market": "KOSDAQ",
      "score": 5,
      "flow_score": 1,
      "trend_score": 3,
      "vol_score": 1,
      "foreign_flow": 1.0,
      "institution_flow": -2.9,
      "volume_ratio": 2.08,
      "signal_strength": "weak",
      "signal_date": "2026-04-22",
      "price": 4870.0,
      "change_pct": 11.31,
      "ma20": 4788,
      "ma60": 3981.0,
      "trend": "above_both"
    }
  ],
  "stats": {
    "total": 43,
    "avg_score": 6.5,
    "strong": 8,
    "moderate": 22,
    "weak": 13
  },
  "processing_time_s": 272.8,
  "updated_at": "2026-04-22T17:49:53.410362"
}